pyrunscope-0.9.0a1.dist-info/DESCRIPTION.rst
pyrunscope-0.9.0a1.dist-info/METADATA
pyrunscope-0.9.0a1.dist-info/RECORD
pyrunscope-0.9.0a1.dist-info/WHEEL
pyrunscope-0.9.0a1.dist-info/metadata.json
pyrunscope-0.9.0a1.dist-info/top_level.txt
runscope/__init__.py
runscope/runscopeclient.py
runscope/admin/__init__.py
runscope/admin/bucket.py
runscope/model/__init__.py
runscope/model/resource.py
runscope/resources/api_description/admin.json
runscope/resources/api_description/bucket.json
runscope/resources/api_description/result.json
runscope/resources/api_description/step.json
runscope/resources/api_description/test.json
runscope/test/__init__.py
runscope/test/test.py
