Metadata-Version: 2.0
Name: pyrunscope
Version: 0.9.0a1
Summary: UNKNOWN
Home-page: http://github.com/drewsonne/pyrunscope
Author: Drew J. Sonne
Author-email: drew.sonne@gmail.com
License: LGPLv2
Platform: UNKNOWN
Requires-Dist: restkit
